swx_sdk/__init__.py
swx_sdk/api_client.py
swx_sdk/configuration.py
swx_sdk/exceptions.py
swx_sdk/model_utils.py
swx_sdk/rest.py
swx_sdk/swx_api_client.py
swx_sdk/api/__init__.py
swx_sdk/api/actions_api.py
swx_sdk/api/collections_api.py
swx_sdk/api/events_api.py
swx_sdk/api/items_api.py
swx_sdk/api/model_versions_api.py
swx_sdk/api/models_api.py
swx_sdk/api/properties_api.py
swx_sdk/api/things_api.py
swx_sdk/apis/__init__.py
swx_sdk/model/__init__.py
swx_sdk/model/action_delay.py
swx_sdk/model/action_delay_input.py
swx_sdk/model/action_delay_input_properties.py
swx_sdk/model/action_delay_input_properties_input.py
swx_sdk/model/action_delay_list_response.py
swx_sdk/model/action_delay_response.py
swx_sdk/model/action_delete_response.py
swx_sdk/model/action_list_response.py
swx_sdk/model/action_reboot.py
swx_sdk/model/action_reboot_response.py
swx_sdk/model/action_request.py
swx_sdk/model/action_request_delay.py
swx_sdk/model/action_request_delay_input.py
swx_sdk/model/action_response_element1.py
swx_sdk/model/action_response_element1_delay.py
swx_sdk/model/action_response_element2.py
swx_sdk/model/action_response_element2_delay.py
swx_sdk/model/action_response_element2_delay_input.py
swx_sdk/model/action_response_element3.py
swx_sdk/model/action_response_element3_reboot.py
swx_sdk/model/action_update_request.py
swx_sdk/model/action_update_request_delay.py
swx_sdk/model/action_update_response.py
swx_sdk/model/action_update_response_delay.py
swx_sdk/model/collection_list_response.py
swx_sdk/model/collection_list_response_paging.py
swx_sdk/model/collection_request.py
swx_sdk/model/collection_response.py
swx_sdk/model/collection_update_request.py
swx_sdk/model/collection_update_response.py
swx_sdk/model/error_response.py
swx_sdk/model/error_response_error.py
swx_sdk/model/event_high_cpu.py
swx_sdk/model/event_high_cpu_data.py
swx_sdk/model/event_high_cpu_list_response.py
swx_sdk/model/event_high_cpu_response.py
swx_sdk/model/event_request.py
SWX_API_Python_SDK-0.16.dist-info/LICENSE
SWX_API_Python_SDK-0.16.dist-info/METADATA
SWX_API_Python_SDK-0.16.dist-info/WHEEL
SWX_API_Python_SDK-0.16.dist-info/top_level.txt
SWX_API_Python_SDK-0.16.dist-info/RECORD
