Metadata-Version: 2.1
Name: SWX-API-Python-SDK
Version: 0.16
Summary: Smartworks API SDK for Python
Home-page: UNKNOWN
Author: Smartworks SDK TF
Author-email: 
License: UNKNOWN
Platform: UNKNOWN
Classifier: Programming Language :: Python :: 3
Classifier: License :: OSI Approved :: MIT License
Classifier: Operating System :: OS Independent
Requires-Python: >=3.6
Requires-Dist: urllib3 (>=1.25.3)
Requires-Dist: python-dateutil
